foo/__init__.py
foodemo30-0.0.1.dist-info/LICENSE
foodemo30-0.0.1.dist-info/METADATA
foodemo30-0.0.1.dist-info/WHEEL
foodemo30-0.0.1.dist-info/top_level.txt
foodemo30-0.0.1.dist-info/RECORD
