Metadata-Version: 2.1
Name: foodemo30
Version: 0.0.1
Summary: Foo demo project the II
Home-page: https://github.com/JelsinPalomino/config-repository
Author: Jelsin Palomino
Author-email: roberto.prevato@gmail.com
License: MIT
Keywords: demo project
Classifier: Development Status :: 5 - Production/Stable
Classifier: License :: OSI Approved :: MIT License
Classifier: Programming Language :: Python :: 3
Classifier: Programming Language :: Python :: 3.9
Classifier: Operating System :: OS Independent
License-File: LICENSE
